spider/SPIDER.py
spider/__init__.py
spider/clustering.py
spider/enrichment.py
spider/ot.py
spider/preprocess.py
spider/svi.py
spider/trajectory.py
spider/util.py
spider/version.py
spider/visualization.py
spider/R_script/__init__.py
spider/R_script/run_SPARKX.R
spider/R_script/run_nnSVG.R
spider/R_script/run_spatalk.R
spider/R_script/run_spatialPCA.R
spider/SpatialDE2/__init__.py
spider/SpatialDE2/aeh.py
spider/SpatialDE2/de_test.py
spider/SpatialDE2/dp_hmrf.py
spider/SpatialDE2/gaussian_process.py
spider/SpatialDE2/io.py
spider/SpatialDE2/svca.py
spider/SpatialDE2/_internal/__init__.py
spider/SpatialDE2/_internal/distance_cache.py
spider/SpatialDE2/_internal/gpflow_helpers.py
spider/SpatialDE2/_internal/kernels.py
spider/SpatialDE2/_internal/models.py
spider/SpatialDE2/_internal/optimizer.py
spider/SpatialDE2/_internal/score_test.py
spider/SpatialDE2/_internal/sm_kernel.py
spider/SpatialDE2/_internal/svca.py
spider/SpatialDE2/_internal/tf_dataset.py
spider/SpatialDE2/_internal/util.py
spider/SpatialDE2/_internal/util_mixture.py
spider/lrdb/__init__.py
spider/lrdb/lrpairs.tsv
spider/lrdb/pathway.tsv
spider/lrdb/pathways.tsv
spider_old/SPIDER.py
spider_old/__init__.py
spider_old/clustering.py
spider_old/enrichment.py
spider_old/ot.py
spider_old/preprocess.py
spider_old/preprocess_record_0415.py
spider_old/svi.py
spider_old/trajectory.py
spider_old/util.py
spider_old/version.py
spider_old/visualization.py
spider_old/R_script/__init__.py
spider_old/SpatialDE2/__init__.py
spider_old/SpatialDE2/aeh.py
spider_old/SpatialDE2/de_test.py
spider_old/SpatialDE2/dp_hmrf.py
spider_old/SpatialDE2/gaussian_process.py
spider_old/SpatialDE2/io.py
spider_old/SpatialDE2/svca.py
spider_old/SpatialDE2/_internal/__init__.py
spider_old/SpatialDE2/_internal/distance_cache.py
spider_old/SpatialDE2/_internal/gpflow_helpers.py
spider_old/SpatialDE2/_internal/kernels.py
spider_old/SpatialDE2/_internal/models.py
spider_old/SpatialDE2/_internal/optimizer.py
spider_st-0.2.5.dist-info/LICENSE
spider_st-0.2.5.dist-info/METADATA
spider_st-0.2.5.dist-info/WHEEL
spider_st-0.2.5.dist-info/top_level.txt
spider_st-0.2.5.dist-info/RECORD
