Metadata-Version: 2.1
Name: spider-st
Version: 0.2.5
Summary: Identifying spatially variable interactions
Home-page: https://github.com/deepomicslab/SPIDER
Author: Li Shiying
Author-email: shiyingli7-c@my.cityu.edu.hk
License: MIT
Classifier: Programming Language :: Python :: 3
Classifier: License :: OSI Approved :: MIT License
Classifier: Operating System :: OS Independent
License-File: LICENSE
Requires-Dist: anndata (>=0.8.0)
Requires-Dist: numpy (==1.23.5)
Requires-Dist: Cython
Requires-Dist: cellrank
Requires-Dist: fa2
Requires-Dist: gseapy
Requires-Dist: h5py
Requires-Dist: igraph
Requires-Dist: leidenalg
Requires-Dist: louvain
Requires-Dist: matplotlib
Requires-Dist: matplotlib-venn
Requires-Dist: networkx
Requires-Dist: numba (==0.56.4)
Requires-Dist: pandas (==1.3.5)
Requires-Dist: plotly
Requires-Dist: pygco
Requires-Dist: scanpy (==1.9.3)
Requires-Dist: scgco
Requires-Dist: scikit-learn (>=1.3.1)
Requires-Dist: scipy
Requires-Dist: scvelo
Requires-Dist: seaborn
Requires-Dist: somde
Requires-Dist: somoclu
Requires-Dist: spatialde
Requires-Dist: stlearn
Requires-Dist: umap-learn
Requires-Dist: statsmodels
Requires-Dist: scprep
Requires-Dist: squidpy
Requires-Dist: magic-impute
Requires-Dist: NaiveDE
Requires-Dist: gpflow
Requires-Dist: statannotations
Requires-Dist: tensorflow (>=2.12)
Requires-Dist: holoviews
